xpectranet/__init__.py
xpectranet/config.py
xpectranet-0.1.1.dist-info/licenses/LICENSE.md
xpectranet-0.1.1.dist-info/licenses/NOTICE
xpectranet-0.1.1.dist-info/METADATA
xpectranet-0.1.1.dist-info/WHEEL
xpectranet-0.1.1.dist-info/top_level.txt
xpectranet-0.1.1.dist-info/RECORD
