Metadata-Version: 2.4
Name: xpectranet
Version: 0.1.1
Summary: Protocol-grade symbolic memory and cognition infrastructure for agents, LLMs, and mesh systems.
Author-email: "Xpectra Data Technologies Ltd." <support@xpectradata.com>
Maintainer-email: "Xpectra Data Technologies Ltd." <support@xpectradata.com>
License: # LICENSE & INTELLECTUAL PROPERTY NOTICE
Project-URL: Homepage, https://xpectranet.com
Project-URL: Documentation, https://xpectranet.com/sdk/docs
Project-URL: Source, https://github.com/XpectraData/xpectranet
Project-URL: Changelog, https://github.com/XpectraData/xpectranet/releases
Keywords: cognition,agents,symbolic memory,LLM,mesh,protocol,audit,remix
Classifier: License :: Other/Proprietary License
Classifier: Programming Language :: Python :: 3.8
Classifier: Programming Language :: Python :: 3.9
Classifier: Programming Language :: Python :: 3.10
Classifier: Programming Language :: Python :: 3.11
Classifier: Operating System :: OS Independent
Classifier: Intended Audience :: Developers
Classifier: Topic :: Scientific/Engineering :: Artificial Intelligence
Classifier: Development Status :: 3 - Alpha
Requires-Python: >=3.8
License-File: LICENSE.md
License-File: NOTICE
Requires-Dist: numpy>=1.23
Provides-Extra: dev
Requires-Dist: pytest; extra == "dev"
Requires-Dist: build; extra == "dev"
Requires-Dist: twine; extra == "dev"
Provides-Extra: docs
Requires-Dist: mkdocs; extra == "docs"
Requires-Dist: mkdocs-material; extra == "docs"
Dynamic: license-file
